simple_gcp_auth/__init__.py
simple_gcp_auth-0.5.0.dist-info/licenses/LICENSE
simple_gcp_auth-0.5.0.dist-info/METADATA
simple_gcp_auth-0.5.0.dist-info/WHEEL
simple_gcp_auth-0.5.0.dist-info/top_level.txt
simple_gcp_auth-0.5.0.dist-info/RECORD
