Metadata-Version: 2.4
Name: simple-gcp-auth
Version: 0.5.0
Summary: Provides simplified credential fetching for Google Cloud Platform.
Author-email: Alexey Shuvalov <alexey@alexeyshuvalov.com>
Project-URL: Homepage, https://github.com/shuvalov/simple-gcp-auth
Project-URL: Bug Tracker, https://github.com/shuvalov/simple-gcp-auth/issues
Classifier: Programming Language :: Python :: 3
Classifier: License :: OSI Approved :: MIT License
Classifier: Operating System :: OS Independent
Requires-Python: >=3.8
License-File: LICENSE
Requires-Dist: google-auth
Requires-Dist: google-auth-oauthlib
Requires-Dist: requests
Requires-Dist: keyring
Requires-Dist: tenacity
Dynamic: license-file
